apidoc.zcml
buildout.cfg
debug.ini
deploy.ini
setup.py
site.zcml
zdaemon.conf
zope.conf
log/README.txt
src/largeblue/__init__.py
src/largeblue/startup.py
src/largeblue.util.egg-info/PKG-INFO
src/largeblue.util.egg-info/SOURCES.txt
src/largeblue.util.egg-info/dependency_links.txt
src/largeblue.util.egg-info/entry_points.txt
src/largeblue.util.egg-info/namespace_packages.txt
src/largeblue.util.egg-info/not-zip-safe
src/largeblue.util.egg-info/paster_plugins.txt
src/largeblue.util.egg-info/requires.txt
src/largeblue.util.egg-info/top_level.txt
src/largeblue/util/README.txt
src/largeblue/util/__init__.py
src/largeblue/util/batch.py
src/largeblue/util/configure.zcml
src/largeblue/util/dependencies.zcml
src/largeblue/util/emailer.py
src/largeblue/util/interfaces.py
var/README.txt