Metadata-Version: 1.0
Name: largeblue.util
Version: 0.1
Summary: Some helpful web dev utilities
Home-page: http://pesto.largeblue.net/trac/browser/largeblue/devel/largeblue.util
Author: James Arthur
Author-email: firstname.lastname@largeblue.com
License: Public Domain
Keywords: zope largeblue util utilities batch email
Platform: UNKNOWN
Classifier: Programming Language :: Python
Classifier: Environment :: Web Environment
Classifier: Topic :: Internet :: WWW/HTTP :: WSGI :: Application
Classifier: Framework :: Zope3
Classifier: Intended Audience :: Developers
Classifier: License :: Public Domain
Classifier: Natural Language :: English
